{"8aYoJeHcoQeoAe4h7SkgsA==":"dsc-160-1256x837.jpeg","PSXK5E2aWp9X9XTxyFq8Ag==":"dsc-180-1256x1884.jpeg","Eh7cpAyuKd7v2QfTuvwvjA==":"dsc-161-1256x837.jpeg","UY91h8fiCPSUS/LDN8+6DA==":"programmer-121x121.png","tnWGUJTiJwM0jV3rSGhMbw==":"pexels-christina-morillo-1181298-1916x1279.jpg","zKZHn5EA+W4sVA/zcKw+3Q==":"dsc_0160-modified-1256x1256.png","HBZtqc66jXQz/cjf62crmA==":"pexels-ylanite-koppens-843266-886x590.jpg","fHUDySqzf1nSxt5M9r5yEw==":"pexels-karolina-grabowska-5706014-886x1329.jpg","gOO+H4O3eHR8ZcGGSBPWzw==":"pexels-nadezhda-moryak-6063551-2000x1333.jpg","sc83dFhwATE+ParA636o2w==":"pexels-gradienta-7135022-2000x3000.jpeg","Dp54+jhDAh2jCS0jeGqtog==":"pexels-miguel-%C3%A1-padri%C3%B1%C3%A1n-2882630-1916x1274.jpg","I7Y9kNn1AzQIjSLZ3BnR3A==":"0-1176x848.png","ad8mEAAxwSbb7dS7UH5TdQ==":"8-548x306.png","A1rhgWjIikJ2dIX8PcageA==":"2-894x302.png","EYfZaPYByVYlaaskscWzZQ==":"3-574x306.png","1WxrDlffxk6BwWhPO1MzVw==":"11-926x330.png","JwXZXpfpb5/ip3aW8nSy/w==":"password_gen_app-1916x1277.png","Xz4ekPdOtPiURTGgONVpZQ==":"mbr-1476x982.jpg","nTSnlT/BcPCDGksOjv9wug==":"leslie%20nguyen%20resume-1-1700x2200.png","Ibkh+qRokiUKFnbXu1BcNw==":"leslie%20nguyen%20resume-2-1700x2200.png","6+iokztuUFWSx+/PB4mpWw==":"img-3733-1476x2173.jpg","JBLT0Il6IWpNdxyeu1Rg+g==":"img-3734-1256x1821.jpg","Cv9QCt6phPVvpSCzTVvvZQ==":"p2concept_touch-1256x1801.png","egvpRwyL7Sp5C/ctq/6A9A==":"p2concept_sensor-1256x1843.png","/t5GZaDnkm/YcPAfR+Rj2Q==":"p2detail_touch-1256x1793.png","+6tIf4zyyMpjYTX3RMT1tQ==":"p2detail_sensor-1256x1793.png","I7ygNjVfo9rUU53EYq4TPg==":"pexels-fauxels-3184435-1256x1882.jpeg","tXMWkogM3suSHgXK7IIzIQ==":"irtaza%20-%20refined%20sketches%20-%20project%203%20-%20cpsc%20581-1900x2495.png","QxlzE/yYyp4/OlG25BNUAQ==":"detail-1-1900x2747.png","AY6Vq6S8jz3T0q/21N0uyA==":"detail-2-1862x2666.png","xzFAphCWARO5V823yeNf8Q==":"prokect3_concept-2136x3025.png"}